redismq/__init__.py
redismq/client.py
redismq/consumer.py
redismq/debugging.py
redismq/producer.py
redismq-1.1.8.dist-info/METADATA
redismq-1.1.8.dist-info/WHEEL
redismq-1.1.8.dist-info/top_level.txt
redismq-1.1.8.dist-info/RECORD
